carcass/__init__.py
carcass/__main__.py
carcass/carcass.py
carcass/options.py
carcass/templates/.gitignore.template
carcass/templates/CONTRIBUTING.template
carcass/templates/LICENSE.template
carcass/templates/README.template
carcass/templates/__init__.template
carcass/templates/bug_report.template
carcass/templates/class.template
carcass/templates/core.template
carcass/templates/exceptions.template
carcass/templates/feature_request.template
carcass/templates/graphconnector.template
carcass/templates/logger.template
carcass/templates/logger_yaml.template
carcass/templates/macos.template
carcass/templates/main.template
carcass/templates/requirements.template
carcass/templates/setup.template
carcass/templates/ubuntu.template
carcass/templates/utils_init.template
carcass/templates/version.template
carcass/templates/windows.template
carcass/templates/flask/404.html
carcass/templates/flask/500.html
carcass/templates/flask/Dockerfile.template
carcass/templates/flask/base.html
carcass/templates/flask/docker-compose.template
carcass/templates/flask/flask.template
carcass/templates/flask/flaskblueprint.template
carcass/templates/flask/flaskconfig.template
carcass/templates/flask/index.html
carcass/utils/__init__.py
carcass/utils/version.py
carcass-1.2.0.dist-info/LICENSE
carcass-1.2.0.dist-info/METADATA
carcass-1.2.0.dist-info/WHEEL
carcass-1.2.0.dist-info/entry_points.txt
carcass-1.2.0.dist-info/top_level.txt
carcass-1.2.0.dist-info/RECORD
