Metadata-Version: 2.1
Name: carcass
Version: 1.2.0
Summary: A Python package to generate python package scaffolding based on best practices
Home-page: https://github.com/msadministrator/carcass
Author: MSAdministrator
Author-email: rickardja@live.com
License: MIT
Keywords: scaffolding,scaffold,python
Platform: UNKNOWN
Requires-Python: >=3.6, <4
Requires-Dist: pick
